coinbase/__init__.py
coinbase/conf.py
coinbase/data.py
coinbase/merchant.py
coinbase/wallet.py
coinbase/exchange/__init__.py
coinbase/exchange/auth.py
coinbase/exchange/market.py
coinbase/exchange/private.py
python_coinbase_client_api-0.0.1.dev9.dist-info/DESCRIPTION.rst
python_coinbase_client_api-0.0.1.dev9.dist-info/METADATA
python_coinbase_client_api-0.0.1.dev9.dist-info/RECORD
python_coinbase_client_api-0.0.1.dev9.dist-info/WHEEL
python_coinbase_client_api-0.0.1.dev9.dist-info/metadata.json
python_coinbase_client_api-0.0.1.dev9.dist-info/top_level.txt
